{
  "user_id": "3040c3e1-aeff-4113-860f-4bc43e3474b3",
  "accounts": [
    {
      "account_id": "acct-5378bffc-5daa-4789-9530-b2a64de21284",
      "name": "Rodriguez PLC Checking",
      "type": "depository",
      "subtype": "checking",
      "holder_category": "individual",
      "balances": {
        "available": 2330.790554306661,
        "current": 2477.7352499905887,
        "limit": null
      },
      "iso_currency_code": "USD",
      "mask": "6952"
    },
    {
      "account_id": "acct-6cf5b122-4ace-422b-94ce-0fde4b8c9d7e",
      "name": "Doyle, Guerrero and Henry Savings",
      "type": "depository",
      "subtype": "savings",
      "holder_category": "individual",
      "balances": {
        "available": 6191.166401102935,
        "current": 6970.4235948865,
        "limit": null
      },
      "iso_currency_code": "USD",
      "mask": "3480"
    },
    {
      "account_id": "acct-60f1e3ce-0c0e-4631-b2d1-c8ab0bb2621d",
      "name": "Hall, Young and Gomez Credit Card",
      "type": "credit",
      "subtype": "credit card",
      "holder_category": "individual",
      "balances": {
        "available": 1332.7519050379872,
        "current": 1550.5485407640517,
        "limit": 4662.481266402598
      },
      "iso_currency_code": "USD",
      "mask": "5750"
    }
  ],
  "transactions": [
    {
      "transaction_id": "txn-ba178f07-8fe0-498d-b3b6-3591d00db1c7",
      "account_id": "acct-5378bffc-5daa-4789-9530-b2a64de21284",
      "date": "2025-05-10",
      "amount": -3016.415140079487,
      "merchant_name": "Direct Deposit",
      "merchant_entity_id": null,
      "payment_channel": "online",
      "personal_finance_category": {
        "primary": "Financial",
        "detailed": "Financial/Income"
      },
      "pending": false,
      "iso_currency_code": "USD"
    },
    {
      "transaction_id": "txn-d1c30cbc-1955-45d7-9695-1437c16b9607",
      "account_id": "acct-5378bffc-5daa-4789-9530-b2a64de21284",
      "date": "2025-05-10",
      "amount": -2594.6177664579986,
      "merchant_name": "Direct Deposit",
      "merchant_entity_id": null,
      "payment_channel": "online",
      "personal_finance_category": {
        "primary": "Financial",
        "detailed": "Financial/Income"
      },
      "pending": false,
      "iso_currency_code": "USD"
    },
    {
      "transaction_id": "txn-2fb81242-d3f9-46cf-88fb-cc348a488b0b",
      "account_id": "acct-5378bffc-5daa-4789-9530-b2a64de21284",
      "date": "2025-05-18",
      "amount": -3741.915976100313,
      "merchant_name": "Direct Deposit",
      "merchant_entity_id": null,
      "payment_channel": "online",
      "personal_finance_category": {
        "primary": "Financial",
        "detailed": "Financial/Income"
      },
      "pending": false,
      "iso_currency_code": "USD"
    },
    {
      "transaction_id": "txn-ce90189c-c1fb-431d-b7c3-9950a35d9e13",
      "account_id": "acct-60f1e3ce-0c0e-4631-b2d1-c8ab0bb2621d",
      "date": "2025-05-18",
      "amount": 370.9362727691585,
      "merchant_name": "MobileCarrier #2",
      "merchant_entity_id": null,
      "payment_channel": "other",
      "personal_finance_category": {
        "primary": "Bills & Utilities",
        "detailed": "Bills & Utilities/Mobile Phone"
      },
      "pending": false,
      "iso_currency_code": "USD"
    },
    {
      "transaction_id": "txn-82ce1b70-638d-4be7-bfaa-b2791ebfe1b5",
      "account_id": "acct-5378bffc-5daa-4789-9530-b2a64de21284",
      "date": "2025-05-19",
      "amount": 312.57715290684973,
      "merchant_name": "PayUtilities #4",
      "merchant_entity_id": null,
      "payment_channel": "online",
      "personal_finance_category": {
        "primary": "Bills & Utilities",
        "detailed": "Bills & Utilities/Utilities"
      },
      "pending": false,
      "iso_currency_code": "USD"
    },
    {
      "transaction_id": "txn-ad5db4a0-e781-4717-9786-0ddf5cec5303",
      "account_id": "acct-60f1e3ce-0c0e-4631-b2d1-c8ab0bb2621d",
      "date": "2025-05-19",
      "amount": 44.35536551171109,
      "merchant_name": "ParkingLot Inc #4",
      "merchant_entity_id": null,
      "payment_channel": "in_store",
      "personal_finance_category": {
        "primary": "Transport",
        "detailed": "Transport/Parking"
      },
      "pending": false,
      "iso_currency_code": "USD"
    },
    {
      "transaction_id": "txn-e0702854-973d-46e6-88c7-c12bc6307572",
      "account_id": "acct-5378bffc-5daa-4789-9530-b2a64de21284",
      "date": "2025-05-20",
      "amount": 35.12587433929199,
      "merchant_name": "QuickFuel #1",
      "merchant_entity_id": null,
      "payment_channel": "online",
      "personal_finance_category": {
        "primary": "Transport",
        "detailed": "Transport/Fuel"
      },
      "pending": false,
      "iso_currency_code": "USD"
    },
    {
      "transaction_id": "txn-6b3778ab-3d17-42c8-a209-27d0bbce3694",
      "account_id": "acct-5378bffc-5daa-4789-9530-b2a64de21284",
      "date": "2025-05-21",
      "amount": 37.344520356625125,
      "merchant_name": "RideShareCo #3",
      "merchant_entity_id": null,
      "payment_channel": "in_store",
      "personal_finance_category": {
        "primary": "Transport",
        "detailed": "Transport/Rideshare"
      },
      "pending": false,
      "iso_currency_code": "USD"
    },
    {
      "transaction_id": "txn-37d2d1a8-6c84-4710-9b2d-dd4f886c53eb",
      "account_id": "acct-60f1e3ce-0c0e-4631-b2d1-c8ab0bb2621d",
      "date": "2025-05-22",
      "amount": 121.22025213538745,
      "merchant_name": "CityTransit #1",
      "merchant_entity_id": null,
      "payment_channel": "in_store",
      "personal_finance_category": {
        "primary": "Transport",
        "detailed": "Transport/Public Transit"
      },
      "pending": false,
      "iso_currency_code": "USD"
    },
    {
      "transaction_id": "txn-5cff072b-40ba-4d89-b4d4-e97303e96ad9",
      "account_id": "acct-5378bffc-5daa-4789-9530-b2a64de21284",
      "date": "2025-05-23",
      "amount": 373.5417294614093,
      "merchant_name": "MobileCarrier #4",
      "merchant_entity_id": null,
      "payment_channel": "other",
      "personal_finance_category": {
        "primary": "Bills & Utilities",
        "detailed": "Bills & Utilities/Mobile Phone"
      },
      "pending": false,
      "iso_currency_code": "USD"
    },
    {
      "transaction_id": "txn-6051c7f4-0789-48ac-ac9f-c2c6d416bf80",
      "account_id": "acct-5378bffc-5daa-4789-9530-b2a64de21284",
      "date": "2025-05-29",
      "amount": 103.34005978859604,
      "merchant_name": "ParkingLot Inc #3",
      "merchant_entity_id": null,
      "payment_channel": "in_store",
      "personal_finance_category": {
        "primary": "Transport",
        "detailed": "Transport/Parking"
      },
      "pending": false,
      "iso_currency_code": "USD"
    },
    {
      "transaction_id": "txn-aaf43024-7300-476e-9cfa-08aa6551d170",
      "account_id": "acct-5378bffc-5daa-4789-9530-b2a64de21284",
      "date": "2025-05-30",
      "amount": 106.65455548156567,
      "merchant_name": "QuickFuel #3",
      "merchant_entity_id": null,
      "payment_channel": "other",
      "personal_finance_category": {
        "primary": "Transport",
        "detailed": "Transport/Fuel"
      },
      "pending": false,
      "iso_currency_code": "USD"
    },
    {
      "transaction_id": "txn-301af736-2f03-482c-b42b-1eb53d128d1a",
      "account_id": "acct-5378bffc-5daa-4789-9530-b2a64de21284",
      "date": "2025-05-31",
      "amount": 275.4670313836341,
      "merchant_name": "PayUtilities #4",
      "merchant_entity_id": null,
      "payment_channel": "online",
      "personal_finance_category": {
        "primary": "Bills & Utilities",
        "detailed": "Bills & Utilities/Utilities"
      },
      "pending": false,
      "iso_currency_code": "USD"
    },
    {
      "transaction_id": "txn-be9d149a-a59f-459e-9f83-8457d9ef7cd1",
      "account_id": "acct-5378bffc-5daa-4789-9530-b2a64de21284",
      "date": "2025-05-31",
      "amount": 115.99118906792049,
      "merchant_name": "RideShareCo #3",
      "merchant_entity_id": null,
      "payment_channel": "online",
      "personal_finance_category": {
        "primary": "Transport",
        "detailed": "Transport/Rideshare"
      },
      "pending": false,
      "iso_currency_code": "USD"
    },
    {
      "transaction_id": "txn-bb0752db-8d20-44fd-9ca4-fc7407dbc20b",
      "account_id": "acct-60f1e3ce-0c0e-4631-b2d1-c8ab0bb2621d",
      "date": "2025-06-02",
      "amount": 66.46261311333356,
      "merchant_name": "MobileCarrier #4",
      "merchant_entity_id": null,
      "payment_channel": "in_store",
      "personal_finance_category": {
        "primary": "Bills & Utilities",
        "detailed": "Bills & Utilities/Mobile Phone"
      },
      "pending": false,
      "iso_currency_code": "USD"
    },
    {
      "transaction_id": "txn-ae194db5-4a80-4409-a748-f1dda248d3bb",
      "account_id": "acct-5378bffc-5daa-4789-9530-b2a64de21284",
      "date": "2025-06-03",
      "amount": 138.44861490440644,
      "merchant_name": "ParkingLot Inc #1",
      "merchant_entity_id": null,
      "payment_channel": "online",
      "personal_finance_category": {
        "primary": "Transport",
        "detailed": "Transport/Parking"
      },
      "pending": false,
      "iso_currency_code": "USD"
    },
    {
      "transaction_id": "txn-7533953e-4417-4a30-bb0c-8de8471286ca",
      "account_id": "acct-5378bffc-5daa-4789-9530-b2a64de21284",
      "date": "2025-06-04",
      "amount": -2881.3844809817415,
      "merchant_name": "Direct Deposit",
      "merchant_entity_id": null,
      "payment_channel": "online",
      "personal_finance_category": {
        "primary": "Financial",
        "detailed": "Financial/Income"
      },
      "pending": false,
      "iso_currency_code": "USD"
    },
    {
      "transaction_id": "txn-bf16ca91-22af-4292-9a92-0df0e3dab8ca",
      "account_id": "acct-5378bffc-5daa-4789-9530-b2a64de21284",
      "date": "2025-06-04",
      "amount": 48.20962146799468,
      "merchant_name": "RideShareCo #2",
      "merchant_entity_id": null,
      "payment_channel": "in_store",
      "personal_finance_category": {
        "primary": "Transport",
        "detailed": "Transport/Rideshare"
      },
      "pending": false,
      "iso_currency_code": "USD"
    },
    {
      "transaction_id": "txn-506183ca-0797-4f9c-ab4c-7bac18fdce70",
      "account_id": "acct-60f1e3ce-0c0e-4631-b2d1-c8ab0bb2621d",
      "date": "2025-06-05",
      "amount": 319.76490862726894,
      "merchant_name": "MobileCarrier #4",
      "merchant_entity_id": null,
      "payment_channel": "in_store",
      "personal_finance_category": {
        "primary": "Bills & Utilities",
        "detailed": "Bills & Utilities/Mobile Phone"
      },
      "pending": false,
      "iso_currency_code": "USD"
    },
    {
      "transaction_id": "txn-4df26f01-3af4-4f33-b3bc-cc4649b00619",
      "account_id": "acct-5378bffc-5daa-4789-9530-b2a64de21284",
      "date": "2025-06-12",
      "amount": -2444.941552807768,
      "merchant_name": "Direct Deposit",
      "merchant_entity_id": null,
      "payment_channel": "online",
      "personal_finance_category": {
        "primary": "Financial",
        "detailed": "Financial/Income"
      },
      "pending": false,
      "iso_currency_code": "USD"
    },
    {
      "transaction_id": "txn-d904fa9a-dde1-4a3c-a97b-20b1227dd558",
      "account_id": "acct-5378bffc-5daa-4789-9530-b2a64de21284",
      "date": "2025-06-13",
      "amount": 25.5514138254795,
      "merchant_name": "QuickFuel #2",
      "merchant_entity_id": null,
      "payment_channel": "online",
      "personal_finance_category": {
        "primary": "Transport",
        "detailed": "Transport/Fuel"
      },
      "pending": false,
      "iso_currency_code": "USD"
    },
    {
      "transaction_id": "txn-634a7211-df8f-449f-8a78-212874a87f62",
      "account_id": "acct-5378bffc-5daa-4789-9530-b2a64de21284",
      "date": "2025-06-15",
      "amount": 47.47937072400772,
      "merchant_name": "QuickFuel #2",
      "merchant_entity_id": null,
      "payment_channel": "online",
      "personal_finance_category": {
        "primary": "Transport",
        "detailed": "Transport/Fuel"
      },
      "pending": false,
      "iso_currency_code": "USD"
    },
    {
      "transaction_id": "txn-83ba61d8-b5a9-4e61-925b-f75bf1c8fc70",
      "account_id": "acct-5378bffc-5daa-4789-9530-b2a64de21284",
      "date": "2025-06-15",
      "amount": 52.32355771636136,
      "merchant_name": "Credit Card Payment",
      "merchant_entity_id": null,
      "payment_channel": "online",
      "personal_finance_category": {
        "primary": "Financial",
        "detailed": "Financial/Payments"
      },
      "pending": false,
      "iso_currency_code": "USD"
    },
    {
      "transaction_id": "txn-c63555b8-6b87-47bc-a766-151fa9a18f22",
      "account_id": "acct-5378bffc-5daa-4789-9530-b2a64de21284",
      "date": "2025-06-16",
      "amount": 277.30677290306653,
      "merchant_name": "PayUtilities #3",
      "merchant_entity_id": null,
      "payment_channel": "online",
      "personal_finance_category": {
        "primary": "Bills & Utilities",
        "detailed": "Bills & Utilities/Utilities"
      },
      "pending": false,
      "iso_currency_code": "USD"
    },
    {
      "transaction_id": "txn-c2d4293b-2b5e-4355-8293-428f271dadd2",
      "account_id": "acct-60f1e3ce-0c0e-4631-b2d1-c8ab0bb2621d",
      "date": "2025-06-16",
      "amount": 149.8613869590734,
      "merchant_name": "MobileCarrier #3",
      "merchant_entity_id": null,
      "payment_channel": "online",
      "personal_finance_category": {
        "primary": "Bills & Utilities",
        "detailed": "Bills & Utilities/Mobile Phone"
      },
      "pending": false,
      "iso_currency_code": "USD"
    },
    {
      "transaction_id": "txn-ddb3a7eb-6c83-4c89-ab55-8909d5a674bf",
      "account_id": "acct-5378bffc-5daa-4789-9530-b2a64de21284",
      "date": "2025-06-18",
      "amount": 256.67139856242073,
      "merchant_name": "PayUtilities #3",
      "merchant_entity_id": null,
      "payment_channel": "other",
      "personal_finance_category": {
        "primary": "Bills & Utilities",
        "detailed": "Bills & Utilities/Utilities"
      },
      "pending": false,
      "iso_currency_code": "USD"
    },
    {
      "transaction_id": "txn-06a43cbe-0ab0-4771-af68-656006932e24",
      "account_id": "acct-5378bffc-5daa-4789-9530-b2a64de21284",
      "date": "2025-06-21",
      "amount": 42.80124180456346,
      "merchant_name": "CityTransit #4",
      "merchant_entity_id": null,
      "payment_channel": "in_store",
      "personal_finance_category": {
        "primary": "Transport",
        "detailed": "Transport/Public Transit"
      },
      "pending": false,
      "iso_currency_code": "USD"
    },
    {
      "transaction_id": "txn-62a42f20-901f-4d0f-b3da-b7ab9e2b5a3a",
      "account_id": "acct-5378bffc-5daa-4789-9530-b2a64de21284",
      "date": "2025-06-22",
      "amount": -717.8043921986119,
      "merchant_name": "Direct Deposit",
      "merchant_entity_id": null,
      "payment_channel": "online",
      "personal_finance_category": {
        "primary": "Financial",
        "detailed": "Financial/Income"
      },
      "pending": false,
      "iso_currency_code": "USD"
    },
    {
      "transaction_id": "txn-087592b4-c50a-4d87-a611-4d0536a5d30d",
      "account_id": "acct-60f1e3ce-0c0e-4631-b2d1-c8ab0bb2621d",
      "date": "2025-06-24",
      "amount": 147.47709960757996,
      "merchant_name": "CityTransit #3",
      "merchant_entity_id": null,
      "payment_channel": "in_store",
      "personal_finance_category": {
        "primary": "Transport",
        "detailed": "Transport/Public Transit"
      },
      "pending": false,
      "iso_currency_code": "USD"
    },
    {
      "transaction_id": "txn-632dffce-0134-4cbc-b3af-44bd658243f9",
      "account_id": "acct-60f1e3ce-0c0e-4631-b2d1-c8ab0bb2621d",
      "date": "2025-06-27",
      "amount": 373.6187747334339,
      "merchant_name": "MobileCarrier #3",
      "merchant_entity_id": null,
      "payment_channel": "online",
      "personal_finance_category": {
        "primary": "Bills & Utilities",
        "detailed": "Bills & Utilities/Mobile Phone"
      },
      "pending": false,
      "iso_currency_code": "USD"
    },
    {
      "transaction_id": "txn-5e5c79a7-3f57-4338-ac17-ffeecd0bd4dc",
      "account_id": "acct-60f1e3ce-0c0e-4631-b2d1-c8ab0bb2621d",
      "date": "2025-06-30",
      "amount": 63.16560144320522,
      "merchant_name": "QuickFuel #4",
      "merchant_entity_id": null,
      "payment_channel": "other",
      "personal_finance_category": {
        "primary": "Transport",
        "detailed": "Transport/Fuel"
      },
      "pending": false,
      "iso_currency_code": "USD"
    },
    {
      "transaction_id": "txn-fb19cd2a-5cff-44b0-b65c-33f780aedfb7",
      "account_id": "acct-5378bffc-5daa-4789-9530-b2a64de21284",
      "date": "2025-07-02",
      "amount": 391.0653041671223,
      "merchant_name": "MobileCarrier #2",
      "merchant_entity_id": null,
      "payment_channel": "online",
      "personal_finance_category": {
        "primary": "Bills & Utilities",
        "detailed": "Bills & Utilities/Mobile Phone"
      },
      "pending": false,
      "iso_currency_code": "USD"
    },
    {
      "transaction_id": "txn-ca1431af-d441-4ab5-8913-a05d53644cf0",
      "account_id": "acct-5378bffc-5daa-4789-9530-b2a64de21284",
      "date": "2025-07-06",
      "amount": 229.25887729484563,
      "merchant_name": "PayUtilities #1",
      "merchant_entity_id": null,
      "payment_channel": "online",
      "personal_finance_category": {
        "primary": "Bills & Utilities",
        "detailed": "Bills & Utilities/Utilities"
      },
      "pending": false,
      "iso_currency_code": "USD"
    },
    {
      "transaction_id": "txn-27bc6fda-e624-4eec-8866-d188154277d7",
      "account_id": "acct-5378bffc-5daa-4789-9530-b2a64de21284",
      "date": "2025-07-08",
      "amount": -3136.322837981069,
      "merchant_name": "Direct Deposit",
      "merchant_entity_id": null,
      "payment_channel": "online",
      "personal_finance_category": {
        "primary": "Financial",
        "detailed": "Financial/Income"
      },
      "pending": false,
      "iso_currency_code": "USD"
    },
    {
      "transaction_id": "txn-1f20c60d-4804-461f-bea3-aef61c663b6f",
      "account_id": "acct-60f1e3ce-0c0e-4631-b2d1-c8ab0bb2621d",
      "date": "2025-07-09",
      "amount": 97.65024553863418,
      "merchant_name": "QuickFuel #1",
      "merchant_entity_id": null,
      "payment_channel": "online",
      "personal_finance_category": {
        "primary": "Transport",
        "detailed": "Transport/Fuel"
      },
      "pending": false,
      "iso_currency_code": "USD"
    },
    {
      "transaction_id": "txn-a1ee8222-1e57-479a-979e-c843e6f839b5",
      "account_id": "acct-5378bffc-5daa-4789-9530-b2a64de21284",
      "date": "2025-07-10",
      "amount": 104.71172696576444,
      "merchant_name": "QuickFuel #3",
      "merchant_entity_id": null,
      "payment_channel": "other",
      "personal_finance_category": {
        "primary": "Transport",
        "detailed": "Transport/Fuel"
      },
      "pending": false,
      "iso_currency_code": "USD"
    },
    {
      "transaction_id": "txn-46bc7dfc-8e02-4c0e-a104-5a613c9d7108",
      "account_id": "acct-5378bffc-5daa-4789-9530-b2a64de21284",
      "date": "2025-07-12",
      "amount": 105.0602706034691,
      "merchant_name": "QuickFuel #4",
      "merchant_entity_id": null,
      "payment_channel": "in_store",
      "personal_finance_category": {
        "primary": "Transport",
        "detailed": "Transport/Fuel"
      },
      "pending": false,
      "iso_currency_code": "USD"
    },
    {
      "transaction_id": "txn-d0549b26-0d9e-45de-9346-dfcaef5940a0",
      "account_id": "acct-5378bffc-5daa-4789-9530-b2a64de21284",
      "date": "2025-07-13",
      "amount": -2180.537071632871,
      "merchant_name": "Direct Deposit",
      "merchant_entity_id": null,
      "payment_channel": "online",
      "personal_finance_category": {
        "primary": "Financial",
        "detailed": "Financial/Income"
      },
      "pending": false,
      "iso_currency_code": "USD"
    },
    {
      "transaction_id": "txn-30d8d5ef-1c30-4217-aee4-6c84438f1c2f",
      "account_id": "acct-60f1e3ce-0c0e-4631-b2d1-c8ab0bb2621d",
      "date": "2025-07-16",
      "amount": 114.7286390574378,
      "merchant_name": "RideShareCo #2",
      "merchant_entity_id": null,
      "payment_channel": "online",
      "personal_finance_category": {
        "primary": "Transport",
        "detailed": "Transport/Rideshare"
      },
      "pending": false,
      "iso_currency_code": "USD"
    },
    {
      "transaction_id": "txn-4e2f38d0-01af-4912-8686-776ae5a54b33",
      "account_id": "acct-60f1e3ce-0c0e-4631-b2d1-c8ab0bb2621d",
      "date": "2025-07-16",
      "amount": 88.94078245116658,
      "merchant_name": "RideShareCo #4",
      "merchant_entity_id": null,
      "payment_channel": "online",
      "personal_finance_category": {
        "primary": "Transport",
        "detailed": "Transport/Rideshare"
      },
      "pending": false,
      "iso_currency_code": "USD"
    },
    {
      "transaction_id": "txn-f3bf24b0-8c20-4223-9ac0-3bac1afb7e4a",
      "account_id": "acct-5378bffc-5daa-4789-9530-b2a64de21284",
      "date": "2025-07-21",
      "amount": 75.79063433057078,
      "merchant_name": "Credit Card Payment",
      "merchant_entity_id": null,
      "payment_channel": "online",
      "personal_finance_category": {
        "primary": "Financial",
        "detailed": "Financial/Payments"
      },
      "pending": false,
      "iso_currency_code": "USD"
    },
    {
      "transaction_id": "txn-94f9e918-3fde-49bd-9807-231573ecb21d",
      "account_id": "acct-60f1e3ce-0c0e-4631-b2d1-c8ab0bb2621d",
      "date": "2025-07-27",
      "amount": 368.487968616711,
      "merchant_name": "MobileCarrier #1",
      "merchant_entity_id": null,
      "payment_channel": "online",
      "personal_finance_category": {
        "primary": "Bills & Utilities",
        "detailed": "Bills & Utilities/Mobile Phone"
      },
      "pending": false,
      "iso_currency_code": "USD"
    },
    {
      "transaction_id": "txn-0d7e89f2-d9de-4bb8-911d-14ec0fad0402",
      "account_id": "acct-5378bffc-5daa-4789-9530-b2a64de21284",
      "date": "2025-07-27",
      "amount": 71.14371083315186,
      "merchant_name": "QuickFuel #3",
      "merchant_entity_id": null,
      "payment_channel": "in_store",
      "personal_finance_category": {
        "primary": "Transport",
        "detailed": "Transport/Fuel"
      },
      "pending": false,
      "iso_currency_code": "USD"
    },
    {
      "transaction_id": "txn-8b7d20fe-7e70-4391-b8a1-6228a7836af7",
      "account_id": "acct-5378bffc-5daa-4789-9530-b2a64de21284",
      "date": "2025-07-28",
      "amount": 140.00767891387295,
      "merchant_name": "PayUtilities #4",
      "merchant_entity_id": null,
      "payment_channel": "online",
      "personal_finance_category": {
        "primary": "Bills & Utilities",
        "detailed": "Bills & Utilities/Utilities"
      },
      "pending": false,
      "iso_currency_code": "USD"
    },
    {
      "transaction_id": "txn-6be07f3f-14af-4b72-9cac-ed78e9aca1a6",
      "account_id": "acct-5378bffc-5daa-4789-9530-b2a64de21284",
      "date": "2025-07-28",
      "amount": 132.34764513590852,
      "merchant_name": "QuickFuel #2",
      "merchant_entity_id": null,
      "payment_channel": "other",
      "personal_finance_category": {
        "primary": "Transport",
        "detailed": "Transport/Fuel"
      },
      "pending": false,
      "iso_currency_code": "USD"
    },
    {
      "transaction_id": "txn-36b592a1-001b-428d-bfc8-3e9349c044cb",
      "account_id": "acct-5378bffc-5daa-4789-9530-b2a64de21284",
      "date": "2025-07-30",
      "amount": -972.1735726374911,
      "merchant_name": "Direct Deposit",
      "merchant_entity_id": null,
      "payment_channel": "online",
      "personal_finance_category": {
        "primary": "Financial",
        "detailed": "Financial/Income"
      },
      "pending": false,
      "iso_currency_code": "USD"
    },
    {
      "transaction_id": "txn-c71cab4d-8081-4f73-9b42-f480ffe45ab1",
      "account_id": "acct-5378bffc-5daa-4789-9530-b2a64de21284",
      "date": "2025-08-01",
      "amount": -3203.691445391676,
      "merchant_name": "Direct Deposit",
      "merchant_entity_id": null,
      "payment_channel": "online",
      "personal_finance_category": {
        "primary": "Financial",
        "detailed": "Financial/Income"
      },
      "pending": false,
      "iso_currency_code": "USD"
    },
    {
      "transaction_id": "txn-34d18628-36b7-434d-8bfd-46a0a954b22f",
      "account_id": "acct-5378bffc-5daa-4789-9530-b2a64de21284",
      "date": "2025-08-02",
      "amount": 86.16169084681461,
      "merchant_name": "RideShareCo #2",
      "merchant_entity_id": null,
      "payment_channel": "in_store",
      "personal_finance_category": {
        "primary": "Transport",
        "detailed": "Transport/Rideshare"
      },
      "pending": false,
      "iso_currency_code": "USD"
    },
    {
      "transaction_id": "txn-b03354d1-f255-4cce-9833-2afb863226e1",
      "account_id": "acct-5378bffc-5daa-4789-9530-b2a64de21284",
      "date": "2025-08-06",
      "amount": -1614.143185219046,
      "merchant_name": "Direct Deposit",
      "merchant_entity_id": null,
      "payment_channel": "online",
      "personal_finance_category": {
        "primary": "Financial",
        "detailed": "Financial/Income"
      },
      "pending": false,
      "iso_currency_code": "USD"
    },
    {
      "transaction_id": "txn-77d319c1-1805-4ab4-8757-6a57bf5138e6",
      "account_id": "acct-5378bffc-5daa-4789-9530-b2a64de21284",
      "date": "2025-08-10",
      "amount": 62.805656113286105,
      "merchant_name": "Credit Card Payment",
      "merchant_entity_id": null,
      "payment_channel": "online",
      "personal_finance_category": {
        "primary": "Financial",
        "detailed": "Financial/Payments"
      },
      "pending": false,
      "iso_currency_code": "USD"
    },
    {
      "transaction_id": "txn-7fff396c-5c5b-4d86-b779-9bdfad8a3180",
      "account_id": "acct-5378bffc-5daa-4789-9530-b2a64de21284",
      "date": "2025-08-12",
      "amount": 64.94666668486798,
      "merchant_name": "RideShareCo #1",
      "merchant_entity_id": null,
      "payment_channel": "online",
      "personal_finance_category": {
        "primary": "Transport",
        "detailed": "Transport/Rideshare"
      },
      "pending": false,
      "iso_currency_code": "USD"
    },
    {
      "transaction_id": "txn-4c757353-cd42-406a-8447-d22a50fbec33",
      "account_id": "acct-5378bffc-5daa-4789-9530-b2a64de21284",
      "date": "2025-08-13",
      "amount": 115.57216961380779,
      "merchant_name": "Credit Card Payment",
      "merchant_entity_id": null,
      "payment_channel": "online",
      "personal_finance_category": {
        "primary": "Financial",
        "detailed": "Financial/Payments"
      },
      "pending": false,
      "iso_currency_code": "USD"
    },
    {
      "transaction_id": "txn-5d5eded8-c3ad-49e0-9558-cf10eeec7b36",
      "account_id": "acct-60f1e3ce-0c0e-4631-b2d1-c8ab0bb2621d",
      "date": "2025-08-14",
      "amount": 211.67642818421828,
      "merchant_name": "PayUtilities #3",
      "merchant_entity_id": null,
      "payment_channel": "in_store",
      "personal_finance_category": {
        "primary": "Bills & Utilities",
        "detailed": "Bills & Utilities/Utilities"
      },
      "pending": false,
      "iso_currency_code": "USD"
    },
    {
      "transaction_id": "txn-e7064a9e-7436-4f1c-ba97-454497a0f6bc",
      "account_id": "acct-5378bffc-5daa-4789-9530-b2a64de21284",
      "date": "2025-08-16",
      "amount": -2400.91732854187,
      "merchant_name": "Direct Deposit",
      "merchant_entity_id": null,
      "payment_channel": "online",
      "personal_finance_category": {
        "primary": "Financial",
        "detailed": "Financial/Income"
      },
      "pending": false,
      "iso_currency_code": "USD"
    },
    {
      "transaction_id": "txn-b028309d-0b22-4d23-8e98-a133b7a0a84d",
      "account_id": "acct-5378bffc-5daa-4789-9530-b2a64de21284",
      "date": "2025-08-18",
      "amount": -2129.7065367566593,
      "merchant_name": "Direct Deposit",
      "merchant_entity_id": null,
      "payment_channel": "online",
      "personal_finance_category": {
        "primary": "Financial",
        "detailed": "Financial/Income"
      },
      "pending": false,
      "iso_currency_code": "USD"
    },
    {
      "transaction_id": "txn-6b084769-bfbe-403c-a728-e23b0220f6f3",
      "account_id": "acct-60f1e3ce-0c0e-4631-b2d1-c8ab0bb2621d",
      "date": "2025-08-22",
      "amount": 88.5450389836298,
      "merchant_name": "ParkingLot Inc #4",
      "merchant_entity_id": null,
      "payment_channel": "online",
      "personal_finance_category": {
        "primary": "Transport",
        "detailed": "Transport/Parking"
      },
      "pending": false,
      "iso_currency_code": "USD"
    },
    {
      "transaction_id": "txn-9355642d-b3df-4803-ab80-3e36fdbdf218",
      "account_id": "acct-5378bffc-5daa-4789-9530-b2a64de21284",
      "date": "2025-08-23",
      "amount": 134.76474002272,
      "merchant_name": "RideShareCo #3",
      "merchant_entity_id": null,
      "payment_channel": "other",
      "personal_finance_category": {
        "primary": "Transport",
        "detailed": "Transport/Rideshare"
      },
      "pending": false,
      "iso_currency_code": "USD"
    },
    {
      "transaction_id": "txn-c18a676e-3c23-4952-b54a-3302960f8bfa",
      "account_id": "acct-5378bffc-5daa-4789-9530-b2a64de21284",
      "date": "2025-08-25",
      "amount": -2360.5936510219362,
      "merchant_name": "Direct Deposit",
      "merchant_entity_id": null,
      "payment_channel": "online",
      "personal_finance_category": {
        "primary": "Financial",
        "detailed": "Financial/Income"
      },
      "pending": false,
      "iso_currency_code": "USD"
    },
    {
      "transaction_id": "txn-09b9020b-bc0d-4b6f-8f9a-90d1e7bee411",
      "account_id": "acct-60f1e3ce-0c0e-4631-b2d1-c8ab0bb2621d",
      "date": "2025-08-28",
      "amount": 147.16092727253206,
      "merchant_name": "PayUtilities #2",
      "merchant_entity_id": null,
      "payment_channel": "in_store",
      "personal_finance_category": {
        "primary": "Bills & Utilities",
        "detailed": "Bills & Utilities/Utilities"
      },
      "pending": false,
      "iso_currency_code": "USD"
    },
    {
      "transaction_id": "txn-5b195fa0-0e55-47b3-94f2-3196b287a95e",
      "account_id": "acct-5378bffc-5daa-4789-9530-b2a64de21284",
      "date": "2025-08-29",
      "amount": -1228.1474609495917,
      "merchant_name": "Direct Deposit",
      "merchant_entity_id": null,
      "payment_channel": "online",
      "personal_finance_category": {
        "primary": "Financial",
        "detailed": "Financial/Income"
      },
      "pending": false,
      "iso_currency_code": "USD"
    },
    {
      "transaction_id": "txn-48afec83-8a53-4142-8c66-c75b58b2e25c",
      "account_id": "acct-5378bffc-5daa-4789-9530-b2a64de21284",
      "date": "2025-08-29",
      "amount": -1796.5131942378914,
      "merchant_name": "Direct Deposit",
      "merchant_entity_id": null,
      "payment_channel": "online",
      "personal_finance_category": {
        "primary": "Financial",
        "detailed": "Financial/Income"
      },
      "pending": false,
      "iso_currency_code": "USD"
    },
    {
      "transaction_id": "txn-9aa893f9-bd05-4dd2-90f8-c2f4d38748a4",
      "account_id": "acct-60f1e3ce-0c0e-4631-b2d1-c8ab0bb2621d",
      "date": "2025-08-29",
      "amount": 145.74347164633463,
      "merchant_name": "PayUtilities #4",
      "merchant_entity_id": null,
      "payment_channel": "online",
      "personal_finance_category": {
        "primary": "Bills & Utilities",
        "detailed": "Bills & Utilities/Utilities"
      },
      "pending": false,
      "iso_currency_code": "USD"
    },
    {
      "transaction_id": "txn-bb8843be-355a-4cc9-a6ff-099bb2aa80bd",
      "account_id": "acct-5378bffc-5daa-4789-9530-b2a64de21284",
      "date": "2025-09-02",
      "amount": -1032.1375521600594,
      "merchant_name": "Direct Deposit",
      "merchant_entity_id": null,
      "payment_channel": "online",
      "personal_finance_category": {
        "primary": "Financial",
        "detailed": "Financial/Income"
      },
      "pending": false,
      "iso_currency_code": "USD"
    },
    {
      "transaction_id": "txn-c602e203-b97f-4c04-b3a2-1012e70942f0",
      "account_id": "acct-5378bffc-5daa-4789-9530-b2a64de21284",
      "date": "2025-09-07",
      "amount": 110.51007911422656,
      "merchant_name": "Credit Card Payment",
      "merchant_entity_id": null,
      "payment_channel": "online",
      "personal_finance_category": {
        "primary": "Financial",
        "detailed": "Financial/Payments"
      },
      "pending": false,
      "iso_currency_code": "USD"
    },
    {
      "transaction_id": "txn-b1ccc9ed-5cb0-4f50-a1b1-df2bd2691f5e",
      "account_id": "acct-5378bffc-5daa-4789-9530-b2a64de21284",
      "date": "2025-09-09",
      "amount": 115.67386699437743,
      "merchant_name": "ParkingLot Inc #1",
      "merchant_entity_id": null,
      "payment_channel": "in_store",
      "personal_finance_category": {
        "primary": "Transport",
        "detailed": "Transport/Parking"
      },
      "pending": false,
      "iso_currency_code": "USD"
    },
    {
      "transaction_id": "txn-9cefba7c-bd9b-476b-9379-9d5389de6f4b",
      "account_id": "acct-5378bffc-5daa-4789-9530-b2a64de21284",
      "date": "2025-09-12",
      "amount": 188.99999617265303,
      "merchant_name": "MobileCarrier #4",
      "merchant_entity_id": null,
      "payment_channel": "online",
      "personal_finance_category": {
        "primary": "Bills & Utilities",
        "detailed": "Bills & Utilities/Mobile Phone"
      },
      "pending": false,
      "iso_currency_code": "USD"
    },
    {
      "transaction_id": "txn-8445548d-97b3-4725-8744-97d757ecc5e6",
      "account_id": "acct-60f1e3ce-0c0e-4631-b2d1-c8ab0bb2621d",
      "date": "2025-09-13",
      "amount": 305.89915784272824,
      "merchant_name": "MobileCarrier #4",
      "merchant_entity_id": null,
      "payment_channel": "online",
      "personal_finance_category": {
        "primary": "Bills & Utilities",
        "detailed": "Bills & Utilities/Mobile Phone"
      },
      "pending": false,
      "iso_currency_code": "USD"
    },
    {
      "transaction_id": "txn-c47d95d5-c373-4b33-a688-601911fecdab",
      "account_id": "acct-5378bffc-5daa-4789-9530-b2a64de21284",
      "date": "2025-09-15",
      "amount": 52.968725278538706,
      "merchant_name": "ParkingLot Inc #3",
      "merchant_entity_id": null,
      "payment_channel": "other",
      "personal_finance_category": {
        "primary": "Transport",
        "detailed": "Transport/Parking"
      },
      "pending": false,
      "iso_currency_code": "USD"
    },
    {
      "transaction_id": "txn-db9d02de-7d19-4da7-b6a9-b0a3e957c62b",
      "account_id": "acct-60f1e3ce-0c0e-4631-b2d1-c8ab0bb2621d",
      "date": "2025-09-17",
      "amount": 357.36553068041337,
      "merchant_name": "PayUtilities #4",
      "merchant_entity_id": null,
      "payment_channel": "online",
      "personal_finance_category": {
        "primary": "Bills & Utilities",
        "detailed": "Bills & Utilities/Utilities"
      },
      "pending": false,
      "iso_currency_code": "USD"
    },
    {
      "transaction_id": "txn-1ed84603-2207-4804-945a-6c068e7bc891",
      "account_id": "acct-60f1e3ce-0c0e-4631-b2d1-c8ab0bb2621d",
      "date": "2025-09-18",
      "amount": 104.44164990437046,
      "merchant_name": "ParkingLot Inc #3",
      "merchant_entity_id": null,
      "payment_channel": "in_store",
      "personal_finance_category": {
        "primary": "Transport",
        "detailed": "Transport/Parking"
      },
      "pending": false,
      "iso_currency_code": "USD"
    },
    {
      "transaction_id": "txn-dda2715e-9556-4ed2-a4ec-fbe711720157",
      "account_id": "acct-60f1e3ce-0c0e-4631-b2d1-c8ab0bb2621d",
      "date": "2025-09-19",
      "amount": 146.23408530359995,
      "merchant_name": "PayUtilities #3",
      "merchant_entity_id": null,
      "payment_channel": "in_store",
      "personal_finance_category": {
        "primary": "Bills & Utilities",
        "detailed": "Bills & Utilities/Utilities"
      },
      "pending": false,
      "iso_currency_code": "USD"
    },
    {
      "transaction_id": "txn-94700e34-9323-4e66-8778-89e6d2087036",
      "account_id": "acct-60f1e3ce-0c0e-4631-b2d1-c8ab0bb2621d",
      "date": "2025-09-19",
      "amount": 141.4759457305504,
      "merchant_name": "RideShareCo #4",
      "merchant_entity_id": null,
      "payment_channel": "other",
      "personal_finance_category": {
        "primary": "Transport",
        "detailed": "Transport/Rideshare"
      },
      "pending": false,
      "iso_currency_code": "USD"
    },
    {
      "transaction_id": "txn-52be41fa-75c8-455c-89fe-e37b789c9056",
      "account_id": "acct-5378bffc-5daa-4789-9530-b2a64de21284",
      "date": "2025-09-20",
      "amount": 154.77035039431203,
      "merchant_name": "MobileCarrier #1",
      "merchant_entity_id": null,
      "payment_channel": "online",
      "personal_finance_category": {
        "primary": "Bills & Utilities",
        "detailed": "Bills & Utilities/Mobile Phone"
      },
      "pending": false,
      "iso_currency_code": "USD"
    },
    {
      "transaction_id": "txn-20a8d519-2da1-433a-a0fa-ad5ac3e84f43",
      "account_id": "acct-5378bffc-5daa-4789-9530-b2a64de21284",
      "date": "2025-09-20",
      "amount": 127.3039021513959,
      "merchant_name": "QuickFuel #2",
      "merchant_entity_id": null,
      "payment_channel": "online",
      "personal_finance_category": {
        "primary": "Transport",
        "detailed": "Transport/Fuel"
      },
      "pending": false,
      "iso_currency_code": "USD"
    },
    {
      "transaction_id": "txn-1861a8d7-c21a-4b3a-98da-05548a275a05",
      "account_id": "acct-5378bffc-5daa-4789-9530-b2a64de21284",
      "date": "2025-09-21",
      "amount": -2261.2719106052873,
      "merchant_name": "Direct Deposit",
      "merchant_entity_id": null,
      "payment_channel": "online",
      "personal_finance_category": {
        "primary": "Financial",
        "detailed": "Financial/Income"
      },
      "pending": false,
      "iso_currency_code": "USD"
    },
    {
      "transaction_id": "txn-c74ede4c-6dd9-4005-8594-c55937005daf",
      "account_id": "acct-5378bffc-5daa-4789-9530-b2a64de21284",
      "date": "2025-09-25",
      "amount": -3185.3991249922783,
      "merchant_name": "Direct Deposit",
      "merchant_entity_id": null,
      "payment_channel": "online",
      "personal_finance_category": {
        "primary": "Financial",
        "detailed": "Financial/Income"
      },
      "pending": false,
      "iso_currency_code": "USD"
    },
    {
      "transaction_id": "txn-680fbb22-14d4-4771-b8c4-d387a896493d",
      "account_id": "acct-60f1e3ce-0c0e-4631-b2d1-c8ab0bb2621d",
      "date": "2025-09-25",
      "amount": 80.9833309625643,
      "merchant_name": "ParkingLot Inc #2",
      "merchant_entity_id": null,
      "payment_channel": "online",
      "personal_finance_category": {
        "primary": "Transport",
        "detailed": "Transport/Parking"
      },
      "pending": false,
      "iso_currency_code": "USD"
    },
    {
      "transaction_id": "txn-1deb1b81-3003-44cd-abd5-68091f0a0a85",
      "account_id": "acct-5378bffc-5daa-4789-9530-b2a64de21284",
      "date": "2025-09-29",
      "amount": -1183.9856781676863,
      "merchant_name": "Direct Deposit",
      "merchant_entity_id": null,
      "payment_channel": "online",
      "personal_finance_category": {
        "primary": "Financial",
        "detailed": "Financial/Income"
      },
      "pending": false,
      "iso_currency_code": "USD"
    },
    {
      "transaction_id": "txn-4b08da5a-49e3-4552-9e37-4b9584ee7b6c",
      "account_id": "acct-60f1e3ce-0c0e-4631-b2d1-c8ab0bb2621d",
      "date": "2025-10-02",
      "amount": 82.48552656339467,
      "merchant_name": "PayUtilities #3",
      "merchant_entity_id": null,
      "payment_channel": "online",
      "personal_finance_category": {
        "primary": "Bills & Utilities",
        "detailed": "Bills & Utilities/Utilities"
      },
      "pending": false,
      "iso_currency_code": "USD"
    },
    {
      "transaction_id": "txn-c3ccc178-3c3f-4e43-af8a-acac3fbffa71",
      "account_id": "acct-5378bffc-5daa-4789-9530-b2a64de21284",
      "date": "2025-10-02",
      "amount": 33.22528496396788,
      "merchant_name": "ParkingLot Inc #1",
      "merchant_entity_id": null,
      "payment_channel": "online",
      "personal_finance_category": {
        "primary": "Transport",
        "detailed": "Transport/Parking"
      },
      "pending": false,
      "iso_currency_code": "USD"
    },
    {
      "transaction_id": "txn-ea2b7efd-2c19-4199-b43f-fa9943270278",
      "account_id": "acct-5378bffc-5daa-4789-9530-b2a64de21284",
      "date": "2025-10-06",
      "amount": -830.2316337856586,
      "merchant_name": "Direct Deposit",
      "merchant_entity_id": null,
      "payment_channel": "online",
      "personal_finance_category": {
        "primary": "Financial",
        "detailed": "Financial/Income"
      },
      "pending": false,
      "iso_currency_code": "USD"
    },
    {
      "transaction_id": "txn-d0bf6d56-b8ef-4cf0-bf48-22d54c395b1d",
      "account_id": "acct-60f1e3ce-0c0e-4631-b2d1-c8ab0bb2621d",
      "date": "2025-10-06",
      "amount": 244.37328205328114,
      "merchant_name": "MobileCarrier #1",
      "merchant_entity_id": null,
      "payment_channel": "other",
      "personal_finance_category": {
        "primary": "Bills & Utilities",
        "detailed": "Bills & Utilities/Mobile Phone"
      },
      "pending": false,
      "iso_currency_code": "USD"
    },
    {
      "transaction_id": "txn-c0e354ad-91ba-4ac1-8687-47b3b17079d3",
      "account_id": "acct-60f1e3ce-0c0e-4631-b2d1-c8ab0bb2621d",
      "date": "2025-10-08",
      "amount": 320.33610639700123,
      "merchant_name": "MobileCarrier #2",
      "merchant_entity_id": null,
      "payment_channel": "online",
      "personal_finance_category": {
        "primary": "Bills & Utilities",
        "detailed": "Bills & Utilities/Mobile Phone"
      },
      "pending": false,
      "iso_currency_code": "USD"
    },
    {
      "transaction_id": "txn-a29f37f7-4e72-47b1-98de-73ffa12f50b6",
      "account_id": "acct-5378bffc-5daa-4789-9530-b2a64de21284",
      "date": "2025-10-09",
      "amount": 81.82452873564655,
      "merchant_name": "ParkingLot Inc #2",
      "merchant_entity_id": null,
      "payment_channel": "in_store",
      "personal_finance_category": {
        "primary": "Transport",
        "detailed": "Transport/Parking"
      },
      "pending": false,
      "iso_currency_code": "USD"
    },
    {
      "transaction_id": "txn-fb247816-2204-4c02-afa0-8c88d11436c8",
      "account_id": "acct-5378bffc-5daa-4789-9530-b2a64de21284",
      "date": "2025-10-10",
      "amount": 147.72552097851997,
      "merchant_name": "Credit Card Payment",
      "merchant_entity_id": null,
      "payment_channel": "online",
      "personal_finance_category": {
        "primary": "Financial",
        "detailed": "Financial/Payments"
      },
      "pending": false,
      "iso_currency_code": "USD"
    },
    {
      "transaction_id": "txn-8cabbd77-19ac-4ec7-8ec7-5a9d7f09f229",
      "account_id": "acct-60f1e3ce-0c0e-4631-b2d1-c8ab0bb2621d",
      "date": "2025-10-11",
      "amount": 60.228472039164174,
      "merchant_name": "MobileCarrier #3",
      "merchant_entity_id": null,
      "payment_channel": "in_store",
      "personal_finance_category": {
        "primary": "Bills & Utilities",
        "detailed": "Bills & Utilities/Mobile Phone"
      },
      "pending": false,
      "iso_currency_code": "USD"
    },
    {
      "transaction_id": "txn-56728b51-a024-40f2-93da-132f62bdccfa",
      "account_id": "acct-5378bffc-5daa-4789-9530-b2a64de21284",
      "date": "2025-10-15",
      "amount": 213.25462200056037,
      "merchant_name": "MobileCarrier #2",
      "merchant_entity_id": null,
      "payment_channel": "other",
      "personal_finance_category": {
        "primary": "Bills & Utilities",
        "detailed": "Bills & Utilities/Mobile Phone"
      },
      "pending": false,
      "iso_currency_code": "USD"
    },
    {
      "transaction_id": "txn-8914bbf6-0d8f-480b-9e10-e8430ae473b4",
      "account_id": "acct-5378bffc-5daa-4789-9530-b2a64de21284",
      "date": "2025-10-16",
      "amount": -3917.427227209398,
      "merchant_name": "Direct Deposit",
      "merchant_entity_id": null,
      "payment_channel": "online",
      "personal_finance_category": {
        "primary": "Financial",
        "detailed": "Financial/Income"
      },
      "pending": false,
      "iso_currency_code": "USD"
    },
    {
      "transaction_id": "txn-1716d3ab-d192-4c8c-a7a6-66a85efc462c",
      "account_id": "acct-5378bffc-5daa-4789-9530-b2a64de21284",
      "date": "2025-10-16",
      "amount": 54.367176000028316,
      "merchant_name": "RideShareCo #4",
      "merchant_entity_id": null,
      "payment_channel": "in_store",
      "personal_finance_category": {
        "primary": "Transport",
        "detailed": "Transport/Rideshare"
      },
      "pending": false,
      "iso_currency_code": "USD"
    },
    {
      "transaction_id": "txn-51a8dd9c-ea0c-4f15-947d-43c0eaf72108",
      "account_id": "acct-60f1e3ce-0c0e-4631-b2d1-c8ab0bb2621d",
      "date": "2025-10-16",
      "amount": 123.82276152112905,
      "merchant_name": "ParkingLot Inc #2",
      "merchant_entity_id": null,
      "payment_channel": "other",
      "personal_finance_category": {
        "primary": "Transport",
        "detailed": "Transport/Parking"
      },
      "pending": false,
      "iso_currency_code": "USD"
    },
    {
      "transaction_id": "txn-f160f190-935a-4a17-8c2b-3a7a6dcaf651",
      "account_id": "acct-60f1e3ce-0c0e-4631-b2d1-c8ab0bb2621d",
      "date": "2025-10-19",
      "amount": 343.69257783969886,
      "merchant_name": "MobileCarrier #1",
      "merchant_entity_id": null,
      "payment_channel": "in_store",
      "personal_finance_category": {
        "primary": "Bills & Utilities",
        "detailed": "Bills & Utilities/Mobile Phone"
      },
      "pending": false,
      "iso_currency_code": "USD"
    },
    {
      "transaction_id": "txn-81fd5ec9-d6b0-419b-940f-ac9d78171125",
      "account_id": "acct-5378bffc-5daa-4789-9530-b2a64de21284",
      "date": "2025-10-20",
      "amount": 91.21643245628518,
      "merchant_name": "RideShareCo #4",
      "merchant_entity_id": null,
      "payment_channel": "in_store",
      "personal_finance_category": {
        "primary": "Transport",
        "detailed": "Transport/Rideshare"
      },
      "pending": false,
      "iso_currency_code": "USD"
    },
    {
      "transaction_id": "txn-79b917f0-d2e6-4213-841d-1afb3efbbbaa",
      "account_id": "acct-5378bffc-5daa-4789-9530-b2a64de21284",
      "date": "2025-10-22",
      "amount": 96.58473052331942,
      "merchant_name": "QuickFuel #2",
      "merchant_entity_id": null,
      "payment_channel": "other",
      "personal_finance_category": {
        "primary": "Transport",
        "detailed": "Transport/Fuel"
      },
      "pending": false,
      "iso_currency_code": "USD"
    },
    {
      "transaction_id": "txn-d8299eeb-f343-46f5-b5e4-60291e96bf1b",
      "account_id": "acct-5378bffc-5daa-4789-9530-b2a64de21284",
      "date": "2025-10-23",
      "amount": -1753.501480279151,
      "merchant_name": "Direct Deposit",
      "merchant_entity_id": null,
      "payment_channel": "online",
      "personal_finance_category": {
        "primary": "Financial",
        "detailed": "Financial/Income"
      },
      "pending": false,
      "iso_currency_code": "USD"
    },
    {
      "transaction_id": "txn-31bc95a9-c839-46f4-8d7d-c2990c767263",
      "account_id": "acct-5378bffc-5daa-4789-9530-b2a64de21284",
      "date": "2025-10-25",
      "amount": 280.3796090168886,
      "merchant_name": "MobileCarrier #1",
      "merchant_entity_id": null,
      "payment_channel": "online",
      "personal_finance_category": {
        "primary": "Bills & Utilities",
        "detailed": "Bills & Utilities/Mobile Phone"
      },
      "pending": false,
      "iso_currency_code": "USD"
    },
    {
      "transaction_id": "txn-78cd615e-855c-4f19-8967-4b6b189d6608",
      "account_id": "acct-5378bffc-5daa-4789-9530-b2a64de21284",
      "date": "2025-10-31",
      "amount": 45.560554572690705,
      "merchant_name": "QuickFuel #4",
      "merchant_entity_id": null,
      "payment_channel": "online",
      "personal_finance_category": {
        "primary": "Transport",
        "detailed": "Transport/Fuel"
      },
      "pending": false,
      "iso_currency_code": "USD"
    },
    {
      "transaction_id": "txn-d135c78f-ca2c-4000-88b2-aea0ff4a9c70",
      "account_id": "acct-5378bffc-5daa-4789-9530-b2a64de21284",
      "date": "2025-11-01",
      "amount": 53.03216065551237,
      "merchant_name": "ParkingLot Inc #1",
      "merchant_entity_id": null,
      "payment_channel": "other",
      "personal_finance_category": {
        "primary": "Transport",
        "detailed": "Transport/Parking"
      },
      "pending": false,
      "iso_currency_code": "USD"
    },
    {
      "transaction_id": "txn-1a9cfaee-adfc-4cbf-98cc-97985241a36d",
      "account_id": "acct-60f1e3ce-0c0e-4631-b2d1-c8ab0bb2621d",
      "date": "2025-11-02",
      "amount": 105.12994629110695,
      "merchant_name": "CityTransit #4",
      "merchant_entity_id": null,
      "payment_channel": "in_store",
      "personal_finance_category": {
        "primary": "Transport",
        "detailed": "Transport/Public Transit"
      },
      "pending": false,
      "iso_currency_code": "USD"
    },
    {
      "transaction_id": "txn-3143fb98-642e-495c-8893-897620af22b1",
      "account_id": "acct-60f1e3ce-0c0e-4631-b2d1-c8ab0bb2621d",
      "date": "2025-11-02",
      "amount": 87.52656834401829,
      "merchant_name": "CityTransit #3",
      "merchant_entity_id": null,
      "payment_channel": "other",
      "personal_finance_category": {
        "primary": "Transport",
        "detailed": "Transport/Public Transit"
      },
      "pending": false,
      "iso_currency_code": "USD"
    }
  ],
  "liabilities": [
    {
      "account_id": "acct-60f1e3ce-0c0e-4631-b2d1-c8ab0bb2621d",
      "aprs": [
        {
          "apr_percentage": 23.36391190663825,
          "apr_type": "purchase_apr"
        }
      ],
      "is_overdue": false,
      "last_payment_amount": 436.58449764697883,
      "last_payment_date": "2025-10-11",
      "last_statement_balance": 1779.3479675211652,
      "minimum_payment_amount": 77.52742703820259,
      "next_payment_due_date": "2025-11-13"
    }
  ]
}